gpulegion/__init__.py
gpulegion/core.py
gpulegion/backends/__init__.py
gpulegion/backends/apple.py
gpulegion/backends/base.py
gpulegion/backends/detector.py
gpulegion/backends/fallback.py
gpulegion/backends/nvidia.py
gpulegion-0.1.1.dist-info/licenses/LICENSE
gpulegion-0.1.1.dist-info/METADATA
gpulegion-0.1.1.dist-info/WHEEL
gpulegion-0.1.1.dist-info/top_level.txt
gpulegion-0.1.1.dist-info/RECORD
