Metadata-Version: 2.4
Name: gpulegion
Version: 0.1.1
Summary: Unified GPU telemetry for Apple Silicon, NVIDIA, and beyond
Author-email: Raja CSP Raman <raja.csp@gmail.com>
License: MIT
Project-URL: Homepage, https://github.com/kactlabs/gpulegion
Project-URL: Repository, https://github.com/kactlabs/gpulegion
Project-URL: Issues, https://github.com/kactlabs/gpulegion/issues
Keywords: gpu,monitoring,apple-silicon,nvidia,telemetry,m1,m2,m3,m4,m5
Classifier: Development Status :: 3 - Alpha
Classifier: Intended Audience :: Developers
Classifier: License :: OSI Approved :: MIT License
Classifier: Operating System :: MacOS
Classifier: Operating System :: POSIX :: Linux
Classifier: Programming Language :: Python :: 3
Classifier: Programming Language :: Python :: 3.9
Classifier: Programming Language :: Python :: 3.10
Classifier: Programming Language :: Python :: 3.11
Classifier: Programming Language :: Python :: 3.12
Classifier: Topic :: System :: Monitoring
Classifier: Topic :: Scientific/Engineering :: Artificial Intelligence
Requires-Python: >=3.9
License-File: LICENSE
Dynamic: license-file
